MANIFEST.in
README.rst
setup.py
django_print_settings/__init__.py
django_print_settings.egg-info/PKG-INFO
django_print_settings.egg-info/SOURCES.txt
django_print_settings.egg-info/dependency_links.txt
django_print_settings.egg-info/not-zip-safe
django_print_settings.egg-info/top_level.txt
django_print_settings/management/__init__.py
django_print_settings/management/commands/__init__.py
django_print_settings/management/commands/print_settings.py