Metadata-Version: 1.1
Name: django-print-settings
Version: 0.1.2
Summary: print_settings management command for Django
Home-page: http://github.com/msabramo/django-print-settings
Author: Marc Abramowitz
Author-email: marc@marc-abramowitz.com
License: New BSD License
Platform: any
Classifier: Development Status :: 4 - Beta
Classifier: Development Status :: 5 - Production/Stable
Classifier: Environment :: Web Environment
Classifier: Framework :: Django
Classifier: Intended Audience :: Developers
Classifier: License :: OSI Approved :: BSD License
Classifier: Operating System :: OS Independent
Classifier: Programming Language :: Python
Classifier: Programming Language :: Python :: 2
Classifier: Programming Language :: Python :: 2.6
Classifier: Programming Language :: Python :: 2.7
Classifier: Programming Language :: Python :: 3
Classifier: Programming Language :: Python :: 3.3
Classifier: Topic :: Utilities
